{
  "title": "毒马铃薯植物",
  "source_url": "https://zh.minecraft.wiki/w/%E6%AF%92%E9%A9%AC%E9%93%83%E8%96%AF%E6%A4%8D%E7%89%A9",
  "text": "此条目描述的是一个愚人节玩笑版本24w14potato中的特性。\n此部分特性仅存在于该愚人节版本中，目前不计划添加到Minecraft的常规版本。\n请注意：该特性的本地化名称以愚人节翻译包为准，原版游戏内的相关内容显示为英文。\n毒马铃薯植物\n[[|]][[|]]\n稀有度\nPotato\n创造标签页（JE）\n马铃薯（Potatoes）\n食物属性\n2（）+1.2饱和度\n最大堆叠\n1\n可再生\n是\n物品ID\npoisonous_potato_plant\n毒马铃薯植物（Poisonous Potato Plant），简称P.P.P.，是会通过任务引导玩家的物品。\n获取\n挖掘\n破坏完全成熟的马铃薯作物时，有1%的概率掉落1个毒马铃薯植物。\n当使用石镐或更好的镐开采毒马铃薯矿石时，有5%的概率掉落1个毒马铃薯植物。使用附有精准采集魔咒的镐开采毒马铃薯矿石不会掉落毒马铃薯植物。\n任意方块被附有薯化魔咒的工具破坏时均有5%的概率掉落1个毒马铃薯植物。\n生物掉落物\n生物\n数量范围 / 掉落概率 / 平均数量\n无抢夺\n抢夺I\n抢夺II\n抢夺III\n蝙薯\n0–1\n33.33%\n0.33\n0–1\n33.33%\n0.33\n0–1\n33.33%\n0.33\n0–1\n33.33%\n0.33\n毒马铃薯僵尸\n0–1\n33.33%\n0.33\n0–1\n33.33%\n0.33\n0–1\n33.33%\n0.33\n0–1\n33.33%\n0.33\n生物\n数量范围 / 掉落概率 / 平均数量\n无抢夺\n抢夺I\n抢夺II\n抢夺III\n蝙薯\n0–1\n1⁄3\n0–1\n1⁄3\n0–1\n1⁄3\n0–1\n1⁄3\n毒马铃薯僵尸\n0–1\n1⁄3\n0–1\n1⁄3\n0–1\n1⁄3\n0–1\n1⁄3\n生物\n掉落数量\n概率 / 平均掉落数量\n无抢夺\n抢夺I\n抢夺II\n抢夺III\n蝙薯\n0\n2⁄3 (66.67%)\n1\n1⁄3 (33.33%)\n平均\n1⁄3 (0.33)\n毒马铃薯僵尸\n0\n2⁄3 (66.67%)\n1\n1⁄3 (33.33%)\n平均\n1⁄3 (0.33)\n掉落总数\n1\n生物\n期望击杀数量\n无抢夺\n抢夺I\n抢夺II\n抢夺III\n蝙薯\n3.00\n毒马铃薯僵尸\n3.00\n仅当被玩家或玩家驯服的狼杀死时。\n箱子战利品\n物品\n来源\n物品数\n堆叠数\n概率\n箱子数\n毒马铃薯植物\n沉船补给箱\n0.34\n1-2\n20.14%\n5.0\n奖励箱\n1.00\n1\n100%\n1.0\n用途\n毒马铃薯植物使用普通的毒马铃薯的纹理。当玩家在物品栏中将鼠标指针悬停在毒马铃薯植物上时，其会出现格鲁乔眼镜的纹理层。虽然名叫植物，但并不能用于种植。\n在物品栏中点击4次之后，毒马铃薯植物的提示框中会出现一条信息：“On closer inspection this 毒马铃薯 is a plant”（仔细端详，毒马铃薯是一名植“务”）\n毒马铃薯植物可以放在玩家的头盔栏中，此时其会开始独白，内容显示在屏幕左上角。\n玩家跳跃或完成特定任务后会触发毒马铃薯植物的下一句独白，或跳过其部分独白。如果玩家从头盔栏中取出毒马铃薯植物并放回，其会重复最后一句独白。\n玩家死亡或掉入马铃薯维度的虚空后，独白的进度会被重置。\n独白\n主条目：24w14potato/potato quest\n修补\n修复和命名毒马铃薯胸甲[[|]][[|]][[|]]\n每个材料可以恢复毒马铃薯胸甲25%的耐久（向下取整）。\n两个毒马铃薯植物之间的交流\n若箱子或陷阱箱中有多个毒马铃薯植物，当玩家打开箱子时会在箱子中随机产生被重命名为各种文本的纸，具体内容如下：\n原文\n译文\n备注\nAre you a plant?\n你是植“务”吗？\nDo you think the Player knows?\n你觉得那个玩家知道吗？\n如该毒马铃薯植物曾被玩家置于头盔槽中，则“the Player”会被替换为对应的玩家名称。\nI think they know\n我觉得他们知道\nLet's stay quiet\n嘘——\nDestroy this message after reading\n阅后即焚\n音效\n字幕\n分类\n描述\n命名空间ID\n本地化键名\n海龟壳：咕咚\n玩家\n装备毒马铃薯植物\nitem.armor.equip_turtle\nsubtitles.item.armor.equip_turtle\n音符盒：播放\n主音量\n毒马铃薯植物与玩家交谈时\nblock.note_block.flute\nsubtitles.block.note_block.note\n数据值\nID\n名称\n命名空间ID\n本地化键名\nPoisonous Potato Plant\npoisonous_potato_plant\nitem.minecraft.poisonous_potato_plant\n物品数据\n参见：物品格式\n默认数据组件结构和字段[源页面]\n物品共通组件\nminecraft:attribute_modifiers：物品为持有者提供的属性修饰符。\nmodifiers：提供的属性修饰符。\n：一个修饰符。\n*\n*amount：计算中修饰符调整基础值的数值。\n*\n*name：当前属性修饰符的名称。\n*\n*operation：定义修饰符对属性的基础值的运算方法。可以为add_value（Op0）、add_multiplied_base（Op1）、add_multiplied_total（Op2）。\nslot：（默认为any）一个装备槽位组，指定修饰符的有效槽位。\n*\n*type：（命名空间ID）一个属性的ID，表示当前属性修饰符要修饰的属性。\n*\n*uuid：当前属性修饰符的UUID。\nshow_in_tooltip：（默认为false）是否显示属性修饰符的提示框。\nminecraft:enchantments：物品的魔咒数据。\nlevels：魔咒数据。\n<魔咒命名空间ID>：（1≤值≤255）一个魔咒和对应魔咒的等级。\nshow_in_tooltip：（默认为false）是否显示魔咒的提示框。\nminecraft:lore：物品的自定义描述信息，共计不允许超过256行。\n：（文本组件）一行描述信息。\nminecraft:max_stack_size：（0≤值≤99）物品的最大堆叠数量。如果此组件不存在，则游戏默认为1。\nminecraft:rarity：物品的基础稀有度。可以为common（常见）、uncommon（少见）、rare（稀有）、epic（史诗）。\nminecraft:repair_cost：（值≥0）物品在铁砧上修理、合并或重命名时在基础经验等级消耗之上额外增加的累积惩罚。\n该物品的其他组件\nminecraft:clicks：玩家在屏幕中点击物品的次数。\nminecraft:hovered：光标是否在GUI中悬在物品上方。\nminecraft:undercover_id：毒马铃薯植物的编号。\nminecraft:views：物品若存在此组件，则玩家打开包含此物品的箱子时此组件的值会增加1。\nminecraft:food：物品的食物属性。\ncan_always_eat：（默认为false）表示物品是否可以无视当前饥饿值食用。\neat_seconds：（默认为1.6）物品食用所需要的时间，以秒为单位。小于0.05秒（1游戏刻）时无法被食用。\n*\n*eat_cound：物品被食用后的音效。\neffects：物品被食用后可能被赋予的状态效果。\n：一项可能施加的状态效果。\n*\n*effect：一项状态效果。\n*\n*id：状态效果的命名空间ID。\nambient：表示状态效果是否是被信标添加的。如果不存在则为false。\namplifier：（无符号8位整数，不小于0且不大于255）状态效果的等级。0表示等级1，以此类推。由于此数字为无符号整数，当值超过127时显示为负数但实际为正数，保存数字s和实际代表数字a的关系为a=256+s。如果不存在则为0。\nduration：距离状态效果失效的时间刻数。如果此值为-1，则此状态效果不会失效。如果不存在则为0。\nshow_icon：表示是否显示状态效果的图标。如果不存在则与show_particles值相同。\nshow_particles：表示是否显示粒子效果。如果不存在则为true。\nprobability：（0≤值≤1，默认为1）食用后施加此状态效果的概率。\n*\n*nutrition：（值≥0）食用物品时增加的饥饿值。\n*\n*saturation_modifier：物品的营养价值。\nJSON\n{\"minecraft:views\":0,\"minecraft:clicks\":0,\"minecraft:enchantments\":{\"levels\":{}},\"minecraft:undercover_id\":0,\"minecraft:attribute_modifiers\":{\"modifiers\":[]},\"minecraft:lore\":[],\"minecraft:max_stack_size\":1,\"minecraft:hovered\":false,\"minecraft:repair_cost\":0,\"minecraft:food\":{\"eat_sound\":\"minecraft:entity.generic.eat\",\"effects\":[{\"effect\":{\"duration\":100,\"id\":\"minecraft:poison\",\"show_icon\":true},\"probability\":0.6}],\"nutrition\":2,\"saturation_modifier\":0.3},\"minecraft:rarity\":\"potato\"}\n在默认组件的基础上，毒马铃薯植物使用下列组件来保存附加数据：\ncomponents：物品附加的数据组件信息。\nminecraft:contacts_messages：与此毒马铃薯植物交流过的毒马铃薯植物的编号列表。\nminecraft:undercover_id：毒马铃薯植物的编号。\nminecraft:views：玩家打开毒马铃薯植物所在的箱子的次数。\n进度\n主条目：进度/24w14potato\n图标\n进度\n游戏内描述\n上游进度\n实际需求（若异）\n仔细端详…\nOn Closer Inspection...\n把毒马铃薯植物放在脸上来揭示真相\nPlace a Poisonous Potato Plant on your head to reveal the truth\n毒马铃薯传奇\n在头盔栏中装备毒马铃薯植物。\n注：获得此进度时不会弹出弹窗。\n你知道吗\n虽然毒马铃薯植物具有食物属性，但实际上无法食用。\n画廊\n鼠标指针未悬停在毒马铃薯植物上时的物品纹理\n鼠标指针悬停在毒马铃薯植物上时的物品纹理\n注释\n在游戏中，这里的词语总会被替换为当前使用语言的“毒马铃薯”物品的名称。\n“Plant”一词本身指植物，但在俚语中也有密探、卧底之意。\n导航"
}