{
  "title": "Earth:绒毛羊",
  "source_url": "https://zh.minecraft.wiki/w/Earth%3A%E7%BB%92%E6%AF%9B%E7%BE%8A",
  "structured_content": {
    "最大生命值": [
      "8（）"
    ],
    "尺寸": [
      "高度：1.3格",
      "宽度：0.9格"
    ],
    "?": [
      "绒毛羊（Fuzzy Sheep）是一种黑色皮肤、长有绒毛的绵羊变种，有着罕见级别的稀有度。"
    ],
    "获取": [
      "绒毛羊可作为罕见级别的生物在羊可点击物中获得。",
      "绒毛羊也可在挑战赛季17中作为奖励获得。"
    ],
    "行为": [
      "主条目：绵羊 § 行为",
      "绒毛羊有着与普通绵羊相同的AI行为，都会漫无目的地游荡，躲避熔岩以及足以造成坠落伤害的悬崖。"
    ],
    "掉落物": [
      "对绒毛羊使用剪刀时掉落：",
      "1-6 白色羊毛",
      "绒毛羊死亡时掉落：",
      "1 白色羊毛",
      "1 生羊肉（若被烧死则掉落熟羊肉）"
    ],
    "Minecraft Earth": [
      "0.33.0",
      "加入了绒毛羊。"
    ]
  }
}