{
  "title": "Java版指南/秘密周五更新9",
  "source_url": "https://zh.minecraft.wiki/w/Java%E7%89%88%E6%8C%87%E5%8D%97%2F%E7%A7%98%E5%AF%86%E5%91%A8%E4%BA%94%E6%9B%B4%E6%96%B09",
  "structured_content": {
    "默认分类": [
      "秘密周五更新9"
    ],
    "发布版本": [
      "Alpha v1.1.0",
      "◄ 秘密周五更新8秘密周六更新1 ►",
      "这篇指南简要概述了Java版秘密周五更新9的更新内容。本指南假定读者对Java版秘密周五更新8的内容有基本了解。"
    ],
    "敌对生物": [
      "可以在多人游戏中生成了。"
    ],
    "新内容": [
      "秘密周五更新9新增物品[[|]]",
      "秘密周五更新9新增物品一览"
    ],
    "[[|]]": [
      "指向世界出生点。"
    ],
    "熔岩桶": [
      "现在可以用作燃料，可以烧炼100个物品。"
    ],
    "多人游戏物品栏": [
      "现在物品栏在多人游戏可用了。"
    ],
    "调试屏幕": [
      "按住F3可以查看调试屏幕。"
    ]
  }
}