{
  "title": "Java版1.16-rc1",
  "source_url": "https://zh.minecraft.wiki/w/Java%E7%89%881.16-rc1",
  "structured_content": {
    "默认分类": [
      "1.16-rc1"
    ],
    "发布时间": [
      "2020年6月18日"
    ],
    "发布候选归属": [
      "1.16"
    ],
    "协议版本": [
      "734"
    ],
    "数据版本": [
      "2565"
    ],
    "资源包版本": [
      "5"
    ],
    "数据包版本": [
      "5",
      "◄◄1.15.2",
      "1.16.1►►",
      "◄1.16-pre8",
      "1.16-rc1是Java版1.16的唯一一个发布候选版本，发布于2020年6月18日，将有关2019冠状病毒病疫情的闪烁标语加入到常规闪烁标语，并修复了一些漏洞。"
    ],
    "闪烁标语": [
      "将有关2019冠状病毒病疫情的闪烁标语加入到常规闪烁标语。",
      "加入了下列闪烁标语：",
      "移除了下列闪烁标语："
    ],
    "Everybody do the Leif!": [
      "<3 Max & 99 & Ducky!"
    ],
    "优化世界": [
      "优化世界的进度条现在根据维度类型进行颜色编码，并根据要优化区块数量计算比例。",
      "绿色代表主世界，棕色代表下界，浅橙色代表末地。",
      "这也适用于自定义世界。"
    ],
    "修复": [
      "修复了20个漏洞",
      "1.16前正式版的漏洞",
      "MC-46257 — 物品不会在黏液块上反弹。",
      "MC-59540 — 无法创建没有任何方块层的超平坦世界。",
      "MC-86197 — 装备盾牌时进食会异常举起盾牌。",
      "MC-88901 — 用盾牌挡住一次攻击会导致视觉上的错误。",
      "MC-93311 — 调整窗口大小后，水纹理图层不会完全覆盖画面。",
      "MC-109121 — 2×2放置的丛林树苗和云杉树苗不会在Y=1处生长。",
      "MC-117312 — 使用从右向左书写的语言会使鼠标停留和点击时出现在错误的位置。",
      "MC-135333 — 打开的栅栏门仍然在水中阻挡玩家。",
      "MC-150543 — 某些情况下使用切石机会导致游戏崩溃。",
      "MC-152934 — 通过发射器放置的水或熔岩会因为超过世界建筑高度而消失。",
      "MC-164224 — 下界荒地、绯红森林和诡异森林中有时会出现未更新的熔岩层。",
      "MC-164569 — 丛林里会随机播放“方块：被破坏”的声音。",
      "MC-166921 — 进食时弓的动画不正确。",
      "MC-166959 — 手持成书点击村民会使其无法进行交易。",
      "MC-174790 — 站在海龟蛋上的生物会令游戏崩溃。",
      "MC-175634 — 饮用时会导致钓鱼竿的鱼线断开。",
      "MC-181313 — 非常高伤害值的箭矢击中实体时服务端崩溃。",
      "1.16开发版本的漏洞",
      "MC-181833 — 在20w18a中游玩世界后再次将其打开会引发崩溃。",
      "MC-182960 — 趋同事项：闪烁标语不一致。",
      "MC-187423 — 某些情况下对末地折跃门使用末影珍珠不起作用。"
    ],
    "你知道吗": [
      "本次加入的闪烁标语中存在多处引用：",
      "“This parrot is no more! It has ceased to be!”引用自Monty Python's Flying Circus。",
      "“Honey, I grew the bees!”引用自1989年的电影Honey, I Shrunk the Kids，同时也在暗示Java版1.15加入的蜜蜂的夸张体型。",
      "“From free range developers!”引用自鸡蛋盒上的文字“From free-range hens”。",
      "“Music by Lena Raine!”引用自Lena Raine为1.16编写新曲的事实。",
      "“Aww man!”引用自CaptainSparklez的改编歌曲Revenge中的歌词“Creeper, aww man”。",
      "“Fabulous graphics!”引用自新加入的“极佳！”画质选项。",
      "“Also try Minecraft Dungeons!”引用自衍生游戏Minecraft Dungeons。",
      "“#minecraftfarms”是Felix Jones使用并试图进入推特动态趋势的话题。"
    ],
    "参考": [
      "Minecraft 1.16 Release Candidate — Minecraft.net，2020年6月18日。",
      "\"Revenge\" - A Minecraft Parody of Usher's DJ Got Us Fallin' In Love (Music Video)，来自CaptainSparklez。YouTube，2011年8月19日。",
      "#minecraftfarms，来自@Xilefian。X（曾名Twitter），2020年6月8日。; just trying to get the hashtag trending，来自@Xilefian。X（曾名Twitter），2020年6月8日。."
    ]
  }
}