{
  "title": "Java版1.7.10-pre3",
  "source_url": "https://zh.minecraft.wiki/w/Java%E7%89%881.7.10-pre3",
  "structured_content": {
    "默认分类": [
      "1.7.10-pre3"
    ],
    "发布时间": [
      "2014年6月10日"
    ],
    "预发布版归属": [
      "1.7.10"
    ],
    "协议版本": [
      "5"
    ],
    "资源包版本": [
      "1",
      "◄◄1.7.9",
      "1.8►►",
      "◄1.7.10-pre2",
      "1.7.10-pre4►",
      "1.7.10-pre3是Java版1.7.10的第3个预发布版，发布于2014年6月10日，以修复Java版1.7.10-pre2中有关服务器断开连接的漏洞。"
    ],
    "修复": [
      "修复了1个漏洞"
    ],
    "其他漏洞": [
      "有关服务器断开连接的漏洞。"
    ],
    "你知道吗": [
      "此版本曾经在启动器中移除，但在2018年9月重新加入。"
    ],
    "参考": [
      "Minecraft 1.7.10 pre-release（存档），来自Searge。Mojang.com，2014年6月3日。",
      "https://twitter.com/SeargeDP/status/476346058130587648"
    ]
  }
}