{
  "title": "Samuel Åberg",
  "source_url": "https://zh.minecraft.wiki/w/Samuel_%C3%85berg",
  "structured_content": {
    "X（Twitter）用户名": [
      "@slamp0000"
    ],
    "Minecraft用户名": [
      "slamp00"
    ],
    "——Samuel Åberg": [
      "萨穆埃尔·奥贝里（Samuel Åberg）在Mojang Studios担任工作室音频总监，他于2015年加入Mojang。"
    ],
    "参与制作的游戏原声集": [
      "Minecraft: The Wild Update (Original Game Soundtrack)（2022年4月20日）"
    ],
    "你知道吗": [
      "为了制作游戏中海豚和熊猫的音效，他前往了科尔莫登野生动物园（Kolmården Wildlife Park）和长隆野生动物世界。",
      "Samuel Åberg在Java版1.9-pre3后被列入鸣谢名单的“音乐与音效”下。"
    ],
    "参见": [
      "C418"
    ],
    "参考": [
      "Talking Dolphins — Minecraft.net，2018年5月19日。",
      "Recording Panda sounds for Minecraft! — YouTube，2018年10月9日。"
    ]
  }
}