{
  "title": "Tutorial:穿越和破坏基岩",
  "source_url": "https://zh.minecraft.wiki/w/Tutorial%3A%E7%A9%BF%E8%B6%8A%E5%92%8C%E7%A0%B4%E5%9D%8F%E5%9F%BA%E5%B2%A9",
  "structured_content": {
    "默认分类": [
      "本文章包含利用漏洞实现的内容。",
      "此漏洞未必对所有版本有效。被修复后，下文所述的信息将不再适用。",
      "请慎重对待。",
      "基岩是一种在生存模式下无法以正常途径破坏的方块。然而，在不使用作弊的生存模式中也能通过漏洞破坏基岩。",
      "主世界底部、下界顶部与底部的基岩层是封闭的。然而，也有利用漏洞穿越它们的办法。",
      "此教程会教你如何在生存模式下穿越基岩层，或者破坏基岩、末地传送门框架等无法在生存模式中通过常规方式破坏的方块。当然，这些方法也可以用于穿越和破坏正常可破坏的方块，只是这没什么实用价值。"
    ],
    "原因": [
      "你可能由于各种原因需要穿越或破坏基岩等方块，例如：",
      "需要在下界中快速旅行，而下界顶部的基岩层上是空的，如果能进入基岩层上方，就可以直接在下界畅通无阻地快速移动。",
      "需要在下界建造刷怪塔，基岩层上方有充足的空间建造。",
      "想要掉进主世界或下界的虚空中。",
      "破坏末地传送门框架，或是末地中的返回传送门。"
    ],
    "穿越基岩": [
      "本章节是关于如何穿越基岩的。这些方法能在不破坏基岩的情况下穿越下界顶部的基岩层。",
      "要注意，在基岩版中，下界的建筑高度限制为127，因此不能在上方建造下界传送门返回主世界，但可以通过重进游戏返回基岩层下方。",
      "方法1",
      "本段落包含利用MC-2164实现的内容。",
      "此漏洞未必对所有版本有效。被修复后，下文所述的信息将不再适用。",
      "请慎重对待。",
      "要使用这个方法，你需要以下材料：",
      "几个末影珍珠。",
      "确保玩家站在下界最顶层基岩下方的两格高的空间里，并确保眼前有一格宽、一格高的空间。把珍珠向前扔进这个空间，然后跳一下。跳跃之前在基岩中受到了窒息才意味着成功。",
      "优点：",
      "很容易得到所需的材料。",
      "一旦掌握了窍门，就很容易做到。",
      "缺点：",
      "可能需要大量的末影珍珠才能成功，且这个方法需要掌握一定的窍门。",
      "在基岩里窒息而带来的伤害，以及使用末影珍珠带来的伤害，有可能导致玩家死亡。",
      "方法1b",
      "本段落包含利用MC-2164实现的内容。",
      "此漏洞未必对所有版本有效。被修复后，下文所述的信息将不再适用。",
      "请慎重对待。",
      "要使用这个方法，你需要以下材料：",
      "几个末影珍珠。",
      "确保玩家站在下界最顶层基岩的正下方。这时，你需要朝上看，然后投掷末影珍珠，并在同时进行跳跃，你会有很大概率穿越基岩。若失败了，多试几次也可以成功。使用这个方法会损失一些生命值，为防止死亡，你可以先吃一个金苹果。",
      "这个方法的原理是：当玩家把末影珍珠扔到离自己非常近的方块上时，玩家会被传送到这个方块里面，而玩家卡在方块里面时可以跳出这个方块，于是玩家便跳出了基岩。",
      "优点：",
      "很容易得到所需的材料。",
      "缺点：",
      "可能需要大量的末影珍珠才能成功，且这个方法需要掌握一定的窍门。",
      "在基岩里窒息而带来的伤害，以及使用末影珍珠带来的伤害，有可能导致玩家死亡。",
      "方法2",
      "本段落包含利用MC-2164实现的内容。",
      "此漏洞未必对所有版本有效。被修复后，下文所述的信息将不再适用。",
      "请慎重对待。",
      "这是最简单的一种方法。",
      "要使用这个方法，你需要以下材料："
    ],
    "一个末影珍珠": [
      "向上挖掘至少挖到Y=126的基岩。将楼梯侧向放置在基岩下方，然后向楼梯上方扔末影珍珠，玩家就会被传送到楼梯的顶部，只要跳几下就可以出去了。",
      "优点：",
      "这很容易做到，不必快速做出反应。",
      "很容易得到需要的材料。"
    ],
    "过时方法": [
      "方法3",
      "本段落所述内容仅适用于Java版。",
      "此章节所介绍的内容已从Minecraft中移除。",
      "此方法依赖的漏洞MC-84198在15w34c中被修复。",
      "这种方法要求玩家已经去过末地外岛。",
      "要使用这个方法，你需要以下材料：",
      "至少一个紫颂果。",
      "最多41组的任意方块",
      "首先，在最顶层的基岩下用方块填满一个17×17、9格高（不计Y=127的基岩）的区域。自然生成的下界岩和基岩已经为你填充了一部分，只需要再填掉空气方块就可以了。",
      "填充完毕后，站在这个区域的顶部（即与顶层的基岩相邻）的正中间（最好记住你的坐标）。然后吃紫颂果，玩家便有概率被传送到基岩层上方。",
      "如果玩家没有被传送到基岩上就再吃紫颂果，直到成功为止。",
      "它的原理是：填充其他所有可被传送到的地方。利用紫颂果的传送能力，当没有其他地方可以被传送时，你只能被传送到基岩上方了。",
      "优点：",
      "你可以在基岩层上方以相同的方式回到基岩下方。",
      "操作很容易。",
      "缺点：",
      "填充如此多方块非常耗时。",
      "它要求玩家已经去过末地外岛，获得了紫颂果。",
      "成功的机会是随机的，所以有可能会消耗大量紫颂果。",
      "方法4",
      "本段落所述内容仅适用于Java版。",
      "此章节所介绍的内容已从Minecraft中移除。",
      "此方法依赖的漏洞MC-3328在20w12a中被修复。",
      "这种方法成本较低，但有极高的死亡概率。还有两种类似的方法，这取决于你放置方块的速度有多快。",
      "要使用这个方法，你需要以下材料：",
      "此章节所介绍的内容已从Minecraft中移除。",
      "下文方法所使用的漏洞已被修复，只适用于旧版本。",
      "方法2c",
      "本段落所述内容仅适用于Java版。",
      "此章节所介绍的内容已从Minecraft中移除。",
      "此方法依赖的漏洞在1.13.2中被修复。",
      "这种方法似乎不是特别复杂，因为它只会破坏最顶层的一个方块，而且它只在下界顶层基岩上面才有用。这些是你需要的材料：",
      "2个黏性活塞",
      "2个普通活塞",
      "10个红石中继器",
      "1个激活铁轨",
      "2个圆石墙",
      "2个TNT矿车",
      "10个黑曜石",
      "2个红石块",
      "5份红石粉",
      "1个拉杆",
      "只消耗其中一个。",
      "会被爆炸破坏且消失。",
      "有了这些材料，请依次完成下面的步骤。因为容易出错，而一旦出错就必须重新开始，所以每一步都提供了示例图片。和方法4一样，也需要制作两个互相垂直的无头活塞，但两个都必须是黏性活塞，下面又演示了一次。",
      "放置两个相互垂直的黏性活塞，并且都朝向你想要破坏的方块。在图中，要被破坏的方块的正上方标记了一个荧石。",
      "在离活塞斜向三个方块远的地方，放置激活铁轨。图中用铁块来表明位置。",
      "黑曜石从激活铁轨后面开始放置，一直延伸到最近的活塞。",
      "把拉杆放在激活铁轨后面的黑曜石上。",
      "将5个中继器从拉杆中引出，在该链的前面放置一个实体方块，再用5个中继器朝着活塞放置。将所有这些延迟设置为最大。",
      "在这个中继器链的末端，放置一个实体方块。再在最近的活塞后面也放置一个实体方块。把一个红石放这两个方块之间。",
      "把两个圆石墙放在你正试图破坏的那个方块的其余两侧。",
      "把TNT矿车放置在激活铁轨上并拉动拉杆。往后站，一个活塞头会被炸掉。重要的是你现在不要关闭拉杆。",
      "把一个红石块放在这个无头活塞的斜上方。关掉拉杆。",
      "在两个活塞之间放置一个实体方块。红石粉将会同时向两个黏性活塞提供信号。",
      "再次重复一遍步骤7-9。",
      "现在，你有了两个无头黏性活塞，清除周围空间，只保留无头活塞和红石块。",
      "放置一个朝下的普通活塞，离一个无头活塞一格远，直接冲着基岩顶部。这可能需要使用另一个活塞。这个活塞面朝的方块必须不可推动的方块（例如是基岩、黑曜石，或者超过了12个方块的推动上限）。",
      "把另外一个普通活塞放在你正试图破坏的方块上，面向上。",
      "走到一个两个无头活塞的背后。这将使你更容易理解，如果你选择跟随图片。",
      "放置一个中继器指向朝上的普通活塞，放一个红石，然后再放另一个中继器对着红石，平行于左边的无头活塞。",
      "放置一个朝向左边无头活塞的中继器，延迟设置为2。再放置两个指向右边无头活塞的中继器，默认延迟。",
      "用红石粉连接这些中继器。在红石粉旁放置一个拉杆并拉下拉杆。",
      "拉下拉杆后，打掉无头活塞旁边的两个红石块。",
      "关闭拉杆。所有的东西都应该恢复正常，黏性活塞又有了头，但是朝下的活塞会神秘地消失，在向上的活塞下面的基岩上有一个洞。",
      "此装置稍作修改还可用于在破坏上方的基岩。为此，请做出以下修改，把装置建在要破坏的基岩下方，红石块的位置改为无头活塞的正下方，并需要把两个普通活塞的朝向反过来。",
      "优点：",
      "可以在游戏初期完成，因为这并不需要太多的材料。",
      "经过少量练习就能很快完成。",
      "缺点：",
      "比较复杂，而且一旦出错可能意味着需要重新开始。",
      "一次只能破坏装置正下方/正上方的一个方块。",
      "步骤1。需要被破坏的方块在荧石的下方",
      "步骤2。放置激活铁轨",
      "步骤3。放置黑曜石来保护红石元件",
      "步骤4。放置拉杆",
      "步骤5 & 6。放置红石元件",
      "步骤7。放置圆石墙",
      "步骤8。GIF展示了将会发生的情况。看起来我把荧石放的离TNT太近了",
      "步骤9。这个红石块让无头活塞保持激活",
      "步骤10。把电路修改为这样将会让另一个黏性活塞没有活塞头",
      "步骤11。这个GIF会展示需要发生什么。荧石不在图片内，因为GIF录制器把它切掉了",
      "步骤12。清理",
      "步骤13。使用另一个活塞来把这个朝下的活塞推到位",
      "步骤14。活塞应该看起来像这样",
      "步骤15。移动到这个位置，以方便解释下面的一些步骤",
      "步骤16。第一组中继器应该看起来像这样",
      "步骤17。与无头活塞连接的中继器应该看起来像这样",
      "步骤18。红石粉应该看起来像这样",
      "步骤19。我认为这是最紧张的时候，因为过一会，你就知道你所做的事情是否是对的",
      "步骤20。GIF展示了需要发生的情况",
      "方法4",
      "本段落所述内容仅适用于Java版。",
      "此章节所介绍的内容已从Minecraft中移除。",
      "此方法依赖的漏洞在1.12中被修复。",
      "这种方法比前面几种方法更简单，但需要更多的材料。这些是你需要破坏一块基岩所需的最少材料："
    ],
    "一个方块": [
      "2辆矿车"
    ],
    "有水下呼吸魔咒的头盔（建议但不强求）": [
      "一直向上挖，直到最顶层（Y=127）的基岩下方。若基岩下方隔一格的地方没有方块，放上。然后把铁轨放在这个方块的顶部，紧挨着基岩。",
      "在铁轨上放一个矿车，然后进入矿车并快速脱离，玩家头部应该会在卡在基岩中，同时受到窒息伤害，这时有水下呼吸魔咒的头盔可以缓解。",
      "接下来，按住跳跃键，然后向正上方扔出一颗末影珍珠。如果没有出来，请再扔一颗。",
      "它的工作原理是在玩家可以跳跃的位置上脱离矿车，并把末影珍珠扔到基岩外，而末影珍珠把玩家传送到基岩顶部。",
      "优点：",
      "它的材料很成本低，而且可以在游戏早期就完成。",
      "操作很容易。",
      "缺点：",
      "如果玩家卡在基岩里时耗尽了末影珍珠，就无法逃生了。",
      "死亡的可能性极高，而且掉落物极有可能会落在基岩外而无法找回。",
      "方法4b",
      "本段落所述内容仅适用于Java版。",
      "此章节所介绍的内容已从Minecraft中移除。",
      "此方法依赖的漏洞MC-3328在20w12a中被修复。",
      "与上一个方法不同的是，玩家需要反应得更快速。",
      "要使用这个方法，你需要以下材料：",
      "2个铁轨",
      "一开始与方法4相同：一辆矿车放在顶层基岩的下面，然后玩家卡入基岩。但之后不同的是，玩家需要不断跳跃，先把铁轨放在基岩层上，再把矿车放在铁轨上，然后快速地坐上它，从而到达基岩层的顶部。",
      "也可以使用船来达到相同效果。",
      "优点：",
      "在此过程中只有窒息伤害，而没有末影珍珠导致的坠落伤害。",
      "尽管不太方便，但它可以设计成矿车电梯的一部分。",
      "缺点：",
      "操作较复杂而困难。",
      "很容易让玩家找不到穿过基岩的具体位置，增加了回去的难度。",
      "方法4c",
      "本段落所述内容仅适用于Java版。",
      "此章节所介绍的内容已从Minecraft中移除。",
      "此方法依赖的漏洞MC-3328在20w12a中被修复。",
      "要使用这个方法，你需要以下材料：",
      "一开始与方法4相同：一辆矿车放在顶层基岩的下面。但之后不同的是，需要破坏铁轨，再利用活塞把下半台阶推到矿车的位置。玩家需要乘上矿车并立即脱离，此时玩家卡入基岩但不受窒息伤害，从而像上两个方法那样到达基岩层的顶部。",
      "优点：",
      "它不像其他方法那样危险，只有坐上矿车时会受到窒息伤害。",
      "玩家不需要快速反应。",
      "缺点：",
      "很难在基岩层中找到一个足够大的空间可以同时放下活塞、台阶和矿车。",
      "很容易让玩家找不到穿过基岩的具体位置。"
    ],
    "一个拉杆": [
      "首先，找到要破的基岩，在底下至少4格的位置放活塞，然后在活塞上放一颗红石粉，最后再通过方块的支持让雪落在红石粉上。接着做反复这样的动作然后激活活塞就可以了。",
      "所应用到的原理：在基岩版中，雪不仅受重力影响，若落在红石粉等方块上还会发生含雪而重合，如果再落下几片雪也会重合。当推动这些重合的雪片后雪片会把重合的部分分离，从而导致雪片替换基岩。",
      "方法9",
      "本段落所述内容仅适用于基岩版。",
      "此章节所介绍的内容已从Minecraft中移除。",
      "此方法依赖的漏洞MCPE-63214在1.16.0中被修复",
      "在基岩版中，雪受重力影响，可以利用雪层来破坏基岩。",
      "你需要以下材料："
    ],
    "破坏基岩": [
      "在靠近基岩层的地方生成的结构有可能替换掉基岩层，但遇到这种事件的概率极低，所以最常用的方法仍然是利用漏洞人工破坏基岩。",
      "破坏基岩必须掌握技巧才能做到，目前有以下几种常用的方法。",
      "方法1",
      "本段落所述内容仅适用于Java版。",
      "本段落包含利用MC-27056实现的内容。",
      "此漏洞未必对所有版本有效。被修复后，下文所述的信息将不再适用。",
      "请慎重对待。",
      "可以快速破坏并替换掉将要收回但没有收回的活塞，来破除基岩。这种方法通常被中文玩家戏称为“铁头功”。",
      "要使用这个方法，你需要以下材料：",
      "至少1个TNT",
      "至少2个活塞",
      "至少1个红石火把等任何红石信号源",
      "在基岩旁放置一个被激活而伸出的活塞，点燃一个TNT，确保TNT的爆炸可以把活塞的信号源以及活塞本身同时破坏。活塞被炸掉的那一瞬间，在原活塞基部的位置放上一个面朝基岩的新活塞。这样基岩就被破坏了。",
      "这个方法需要确保在爆炸的一瞬间放置活塞，可以使用频率远大于20次/秒的鼠标右键的连点器，或者在“游戏菜单”-“选项...”-“按键控制...”-“按键绑定...”-“游戏内容”中，将“使用物品/放置方块”的控制换成键盘上某个暂时无用的按键，如B，此时长按该按键就能实现高速连点的效果。可参考[1]。",
      "这种方法的原理是，活塞的信号源被TNT炸毁后，活塞计划收回，但紧接着活塞就被替换为了另一个普通活塞。新放置的活塞继承了这个收回的计划，却把朝向的基岩误当作活塞臂，从而使基岩消失。因此成功的前提是信号源的炸毁时间先于活塞，而游戏中爆炸的破坏顺序是随机的，因此这个方法并不是百分之百成功，可能需要进行多次尝试。",
      "这个方法最早由Myren Eario发现，可以参考他发布的视频：",
      "优点：",
      "可以在游戏初期完成，因为这并不需要太多的材料。",
      "经过少量练习就能很快完成。",
      "可以破坏任意方向的基岩。",
      "缺点：",
      "成功率低，难以把握时机，即使把握了时机也不是百分之百成功。",
      "易被TNT炸伤，甚至死亡。",
      "方法1b",
      "本段落所述内容仅适用于Java版。",
      "本段落包含利用MC-27056实现的内容。",
      "此漏洞未必对所有版本有效。被修复后，下文所述的信息将不再适用。",
      "请慎重对待。",
      "这个方法与方法1类似。",
      "要使用这个方法，你需要以下材料：",
      "至少2个TNT",
      "至少1个普通活塞",
      "至少1个红石火把等任何红石信号源",
      "这个方法同样需要在基岩旁放置一个被激活而伸出的活塞。之后要在同一游戏刻先后激活两个TNT，确保第一个TNT的爆炸会把活塞的信号源破坏但要保留活塞，第二个TNT可以把活塞破坏。通常使用爆炸抗性大于4的方块把信号源及活塞隔开，以确保第一个TNT的爆炸不会破坏活塞；需要利用红石元件的微观时序来确保两个TNT的先后爆炸顺序。下图是一个典型的例子：",
      "和方法1一样，活塞被炸掉的那一瞬间，需要在原活塞基部的位置放上另一个普通活塞，且新放置的普通活塞面朝基岩。这样基岩就会被破坏。",
      "这种方法的原理与方法1相同，但不再基于游戏的随机爆炸顺序，因此只要把握住时机成功放置普通活塞，基岩被破除的概率为百分之百。",
      "这个方法最早由Fallen_Breath发布，可以参考他发布的视频[2]以及[3]，或[4]。视频内提供了部分可行方法的参考。",
      "优点：",
      "可以在游戏初期完成，因为这并不需要太多的材料。",
      "经过少量练习就能很快完成。",
      "可以破坏任意方向的基岩。",
      "相比方法1更容易把握放置的时机。",
      "在TNT的爆炸特性下，相比方法1更加安全。",
      "缺点：",
      "易被TNT炸伤，甚至死亡。",
      "要求玩家详细了解红石元件的微观时序，才能够搭建出合适的结构。",
      "方法2",
      "本段落所述内容仅适用于Java版。",
      "本段落包含利用MC-27056实现的内容。",
      "此漏洞未必对所有版本有效。被修复后，下文所述的信息将不再适用。",
      "请慎重对待。",
      "可以利用无头活塞来破除基岩。",
      "要使用这个方法，你需要以下材料：",
      "2个黏性活塞",
      "3个普通活塞",
      "1个黏液块",
      "10个红石中继器",
      "4个红石比较器",
      "1个激活铁轨",
      "2个圆石墙",
      "2个TNT矿车",
      "10个黑曜石",
      "2个红石块",
      "7份红石粉",
      "1个拉杆"
    ],
    "一些普通的方块": [
      "只消耗其中一个。",
      "会被爆炸破坏且消失。",
      "有了这些材料，请依次完成下面的步骤。因为容易出错，而一旦出错就必须重新开始，所以每一步都提供了示例图片。",
      "放置两个相互垂直的活塞，一个是黏性活塞，一个是普通活塞，并且都朝向你想要破坏的方块。在图中，要被破坏的方块的正上方标记了一个荧石。",
      "在离活塞斜向三个方块远的地方，放置激活铁轨。图中用铁块来表明位置。",
      "黑曜石从激活铁轨后面开始放置，一直延伸到最近的活塞。",
      "把拉杆放在激活铁轨后面的黑曜石上。",
      "将5个中继器从拉杆中引出，在该链的前面放置一个方块，再用5个中继器朝着活塞放置。将所有中继器的延迟设置为最大。",
      "在这个中继器链的末端，放置一个方块。再在最近的活塞后面也放置一个方块。把一个红石放在这两个方块之间。",
      "把两个圆石墙放在你要破坏的方块的其余两侧。"
    ],
    "把TNT矿车放置在激活铁轨上并拉动拉杆。往后站，一个活塞头会被炸掉。此时不要关闭拉杆！": [
      "把一个红石块放在这个无头活塞的上方。关掉拉杆。",
      "在两个活塞之间放置一个方块。红石粉将会同时向两个活塞提供信号。",
      "重复一遍步骤7-9。",
      "现在，你有了两个无头活塞，清除周围空间，只保留无头活塞和红石块。",
      "在普通活塞前依次放置朝上的普通活塞、朝下的普通活塞、三个普通的方块。面朝下的活塞面朝的方块必须不可推动（例如基岩、黑曜石，或者超过了12个方块的推动上限）。",
      "在黏性无头活塞异侧的方块旁放置一个黏液块，相隔一格，再放置一个朝向黏液块的黏性活塞。",
      "在该黏性活塞后放置4个实体方块。在两个无头活塞后放置3个红石粉。",
      "在方块旁放置中继器、比较器、中继器、比较器，在这些方块后面再放置比较器、比较器、中继器、中继器。用红石线把它们连接起来，并放上拉杆。",
      "拉下拉杆后，破坏掉那两个红石块。",
      "关闭拉杆。所有的东西都应该恢复正常，活塞又有了头，然而，朝下的活塞连同朝上的活塞下面的基岩都已经消失了。",
      "这种方法的工作原理是使用TNT矿车的爆炸来炸毁活塞头，而保留它的底部。结合完美的计时，使得活塞在TNT矿车爆炸的精确的时间内伸出。无头活塞的行为在Tutorial:无头活塞中有详细解释。",
      "此装置稍作修改还可用于在破坏上方的基岩。为此，请做出以下修改：把装置建在要破坏的基岩下方，红石块的位置改为无头活塞的正下方，并需要把两个普通活塞的朝向反过来。",
      "优点：",
      "可以在游戏初期完成，因为这并不需要太多的材料。",
      "经过少量练习就能很快完成。",
      "缺点：",
      "比较复杂，而且一旦出错可能意味着需要重新开始。",
      "一次只能破坏装置正下方/正上方的一个方块。",
      "步骤1。需要被破坏的基岩在荧石的下方",
      "步骤2。放置激活铁轨",
      "步骤3。放置黑曜石来保护红石元件",
      "步骤4。放置拉杆",
      "步骤5 & 6。放置红石元件",
      "步骤7。放置圆石墙",
      "步骤8。放置TNT矿车并拉下拉杆",
      "步骤9。这个红石块让无头活塞保持激活",
      "步骤10。把电路修改为这样将会让另一个黏性活塞没有活塞头",
      "步骤11。爆炸完毕并放置红石块",
      "步骤12。清理",
      "步骤13 & 14。放置活塞和方块",
      "步骤15。放置方块和红石粉",
      "步骤16。放置红石元件",
      "步骤17。拉下拉杆，破坏掉那两个红石块",
      "步骤18。关闭拉杆之后，应该看起来像这样",
      "方法2b",
      "本段落所述内容仅适用于Java版。",
      "也可以做出两个并列无头活塞，并使用下图中的方法破坏基岩。要求：用黏液球标记的两个活塞必须是黏性活塞，用木棍标记的两个活塞种类必须相同（要么都是普通活塞，要么都是黏性活塞）。",
      "关闭拉杆后，看起来应该像这样。此时物品展示框下的基岩已经被破坏。",
      "关于如何做出两个并列的无头活塞，详见Tutorial:无头活塞。"
    ],
    "一个任意方块": [
      "31 - 481个红石",
      "2 - 32个红石中继器",
      "1个拉杆",
      "这一数字会随着玩家的渲染距离或服务器server.properties里的“view-distance”而大量变化。你需要的中继器数量与其相同，红石的数量是它的15倍。",
      "该方法非常容易完成，但是很消耗时间。你需要：",
      "放置一个任意方块。",
      "放置红石火把于这个方块的一侧。",
      "把活塞放在红石火把正上方。",
      "把龙蛋放在活塞臂上。龙蛋应该在你想破坏的方块的正上方。",
      "在那个任意方块的另一侧放置一个朝向这个方块的中继器。",
      "把红石线在中继器后面放成一条直线。每隔15条红石线就放一个红石中继器。然后在直线末尾放置一个拉杆。",
      "启动拉杆，等待5秒钟，然后将其关闭。",
      "走回去，你可以看到龙蛋替换了下面的方块。",
      "这是因为龙蛋掉落在弱加载区块里。在弱加载区块中，下落的方块会立即掉落。但龙蛋有一种特殊的性质，如果它在弱加载区块里掉落，就会替换掉下面的方块。",
      "也可以使用一个区块弱加载检测器来控制活塞，比如下图的装置。玩家只需要远离这个装置使其所在的区块变为弱加载，并等待几秒钟，就可以成功破除基岩。",
      "优点：",
      "如果玩家成功地获得多个龙蛋，可以在活塞前附着许多告示牌，把多个龙蛋放置在告示牌上，这样就可以一次性破坏多个基岩。可以用一个重力方块复制机来复制龙蛋。",
      "因其基于下落的方块机制，所以玩家可以在很高的地方建造这个装置，只要龙蛋可以落到基岩上就行。",
      "缺点：",
      "如果龙蛋掉落出主世界或下界的底部基岩层，它就永远消失了。",
      "在多人游戏中，其他玩家可能会在装置运行时靠近，从而加载到了弱加载区块，导致计划失败。",
      "无法在出生点附近的区块里建造，因为这些区块在该方法适用的版本中永远强加载。",
      "方法5",
      "这可以用多种不同的方法来完成，因为它使用一些具有破坏方块性质的植物："
    ],
    "丛林树或者深色橡木": [
      "此章节所介绍的内容已从Minecraft中移除。",
      "此方法依赖的漏洞MC-10176在1.8.2-pre4中被修复。",
      "巨大的丛林树生长出来时可以替换方块。",
      "巨大的深色橡木在生长时如果侦测到上方存在原木方块有可能向下生长并替换下方两格高度内的方块为深色橡木原木。"
    ],
    "巨型蘑菇": [
      "巨型蘑菇生长出来时，菌盖能替换掉其他方块。"
    ],
    "竹子": [
      "本段落所述内容仅适用于Java版。",
      "此章节所介绍的内容已从Minecraft中移除。",
      "这些特性曾存在于游戏中，但已被移除。",
      "用骨粉催熟竹子可以破除上面的方块。",
      "优点：",
      "这些植物非常容易获得。",
      "这种方法的材料成本低，只需要一些骨粉。",
      "缺点：",
      "植物的生长是不可预知的，所以你可能破坏一些你不想破坏的方块。",
      "这些植物生长有非常严格的空间要求，所以利用它们破坏基岩可能需要多次反复试验。",
      "方法6",
      "本段落所述内容仅适用于Java版。",
      "此章节所介绍的内容已从Minecraft中移除。",
      "此方法依赖的漏洞MC-91528在1.13中被修复。",
      "这种方法需要一个不可破坏的末地水晶和一个活塞。",
      "要做到这一点，只需要把不可破坏的末地水晶用活塞推入你想破坏的那个方块里面，方块就会被破坏。",
      "它的原理是不可破坏的末地水晶会持续在下方产生火，替换掉包括基岩在内的所有方块。",
      "优点：",
      "一旦获得了材料，就很容易完成。",
      "通过使用飞行器来实施此方法，从而可以快速地破除许多基岩。",
      "缺点：",
      "不可破坏的末地水晶很难获得和移动。",
      "很难预测哪个方块会被破坏。",
      "你知道吗：在1.8更新中，黑曜石柱上没有基岩。因为末地水晶产生的火比预期的要低1个方块，破坏了原本应该在那里的基岩。",
      "方法7",
      "本段落所述内容仅适用于基岩版。",
      "此章节所介绍的内容已从Minecraft中移除。",
      "这些特性曾存在于游戏中，但已被移除。",
      "你只需一片雪，一个告示牌以及一个能放置告示牌的方块。 首先，找好你要破坏的基岩，然后隔一格放置一个方块。将告示牌放在基岩的对面，将雪对准告示牌放置，你会发现基岩被雪替换了。",
      "优点：",
      "操作极其简单。",
      "缺点：",
      "雪不易获得。",
      "方法8",
      "本段落所述内容仅适用于基岩版。",
      "此章节所介绍的内容已从Minecraft中移除。",
      "此方法依赖的漏洞MCPE-63214在1.16.0中被修复",
      "你需要以下材料："
    ],
    "一个侦测器": [
      "制作图中的装置，触发侦测器即可破除上方的基岩。要求：左侧的雪层不多于3片，左右两个雪层之和大于8片。中继器的延迟总共为5刻。",
      "这种装置可以扩展，从而一次性破除多个基岩，如下图所示。",
      "还有如下图的装置，拉下拉杆后即可破坏基岩。要求：左侧的雪层不多于3片，左右两个雪层之和大于8片。",
      "这些装置的原理是，下落的雪是一个实体，可以被活塞推动。低于4层的雪没有碰撞箱，从而可以把“下落的雪”实体推入其中，之后转化为雪层方块并堆叠其上，从而可以破坏掉基岩。",
      "方法10",
      "本段落所述内容仅适用于基岩版。",
      "此章节所介绍的内容已从Minecraft中移除。",
      "此方法依赖的漏洞MCPE-131177在1.17.20.20中被修复。",
      "当炼药锅中已有细雪时，再对其使用细雪桶会导致炼药锅上方方块被替换成细雪，以此破坏炼药锅上方的基岩。",
      "你需要以下材料:",
      "2桶细雪",
      "1个炼药锅",
      "将炼药锅放置在要破坏的基岩的正下方，基岩与炼药锅之间不能有空隙。",
      "将两桶细雪填入炼药锅。挖开炼药锅，炼药锅上方的基岩已被破坏。",
      "优点：",
      "材料常见且收集方便。",
      "成功率100%。",
      "结构简单。",
      "缺点：",
      "只能向上破基岩。",
      "方法11",
      "本段落所述内容仅适用于Java版。",
      "此章节所介绍的内容已从Minecraft中移除。",
      "这些特性曾存在于游戏中，但已被移除。",
      "这个方法需要在进入下界的传送门正上方的基岩顶部有一个一格深、1×4大小的洞。这种方法只适用于下界的上层基岩，并且要求在主世界上的128个方块或下界16个方块的范围之内没有其他的下界传送门。",
      "要使用这个方法，你需要以下材料：",
      "大量火把、线等不完整方块。",
      "在这个下界传送门水平距离16个方块以内，所有上方为空气的方块的上方都要放置上准备的方块。",
      "破坏把玩家带到下界的这个传送门。",
      "在至少16个方块之外建造另一个新传送门，然后用它返回到主世界。",
      "回到最开始的传送门，用它回到下界。下界传送门会在下界的顶部生成，并且会替换掉一些基岩。重复这个操作，以破坏更多的基岩。",
      "这个方法是通过删除下界传送门的所有有效位置来实现的。它迫使传送门在基岩上生成，从而黑曜石会替换掉一些基岩。",
      "优点：",
      "此方法非常容易做到，且速度很快。",
      "缺点：",
      "它需要在周围做很多准备。",
      "它要求玩家已经使用其他方法破坏基岩并得到所需的洞。",
      "方法12",
      "本段落所述内容仅适用于Java版。",
      "此章节所介绍的内容已从Minecraft中移除。",
      "此方法依赖的漏洞MC-213813在21w06a中被修复。",
      "要使用这个方法，你需要以下材料："
    ],
    "一些骨粉": [
      "在你需要破坏的基岩下方放置黏土并种上小型垂滴叶，使用骨粉将小型垂滴叶催熟成大型垂滴叶，大型垂滴叶会破坏上方的基岩。",
      "优点：",
      "材料常见且收集方便。",
      "成功率100%。",
      "结构简单。",
      "此方法非常容易做到，且速度很快。",
      "缺点：",
      "运气不好可能需要消耗大量骨粉。"
    ]
  }
}