{
  "title": "地毯/DV",
  "source_url": "https://zh.minecraft.wiki/w/%E5%9C%B0%E6%AF%AF%2FDV",
  "structured_content": {
    "描述": [
      "0"
    ],
    "白色地毯": [
      "1"
    ],
    "橙色地毯": [
      "2"
    ],
    "品红色地毯": [
      "3"
    ],
    "淡蓝色地毯": [
      "4"
    ],
    "黄色地毯": [
      "5"
    ],
    "黄绿色地毯": [
      "6"
    ],
    "粉红色地毯": [
      "7"
    ],
    "灰色地毯": [
      "8"
    ],
    "淡灰色地毯": [
      "9"
    ],
    "青色地毯": [
      "10"
    ],
    "紫色地毯": [
      "11"
    ],
    "蓝色地毯": [
      "12"
    ],
    "棕色地毯": [
      "13"
    ],
    "绿色地毯": [
      "14"
    ],
    "红色地毯": [
      "15"
    ]
  }
}