{
  "title": "基岩版1.13.0.6",
  "source_url": "https://zh.minecraft.wiki/w/%E5%9F%BA%E5%B2%A9%E7%89%881.13.0.6",
  "structured_content": {
    "默认分类": [
      "1.13.0.6"
    ],
    "版本码": [
      "Android：",
      "871130006（armeabi-v7a，26）",
      "872130006（x86，26）"
    ],
    "发布时间": [
      "Xbox One, Windows 10 - 2019年8月14日",
      "Android - 2019年8月15日"
    ],
    "测试版归属": [
      "1.13.0"
    ],
    "协议版本": [
      "371",
      "◄◄1.12.1",
      "1.13.1►►",
      "◄1.13.0.5",
      "1.13.0.9►",
      "beta 1.13.0.6是1.13.0的第5个测试版本，在Android上发布于2019年8月15日，而在Xbox One和Windows 10上发布于8月14日，修复了漏洞。"
    ],
    "修复": [
      "修复了5个漏洞"
    ],
    "崩溃和性能": [
      "修复了游戏过程中可能发生的一些崩溃。",
      "修复了一个当预览含结构空位的结构时可能发生的崩溃。",
      "修复了一个阻止游戏在某些Android设备上正确加载的崩溃。(MCPE-48313)"
    ],
    "常规": [
      "现在，在更新后启动游戏时，游戏中的beta版本说明会正确显示。",
      "现在在传送时设置y旋转时，会将其偏差正确校正为0度而不是-180度。"
    ],
    "参考": [
      "Minecraft Beta - 1.13.0.6 (Xbox One/Windows 10/Android) — Minecraft Feedback，2019年8月14日。"
    ]
  }
}