{
  "title": "掠夺者/ED",
  "source_url": "https://zh.minecraft.wiki/w/%E6%8E%A0%E5%A4%BA%E8%80%85%2FED",
  "structured_content": {
    "实体数据": [
      "实体共通标签，见Template:Nbt inherit/entity/source",
      "生物共通标签，见Template:Nbt inherit/living entity/source",
      "AI生物共通标签，见Template:Nbt inherit/mob/source",
      "袭击者共通标签，见Template:Nbt inherit/raidable/source"
    ],
    "*": [
      "*Inventory：掠夺者存储的物品栏，此标签最多容纳5组物品。当读取时，如果列表数量超过5，则超出范围的物品尝试与范围内的物品合并，如果无法合并则被删除。",
      "物品共通标签，见Template:Nbt inherit/itemnoslot/source"
    ]
  }
}