{
  "title": "毒马铃薯油",
  "source_url": "https://zh.minecraft.wiki/w/%E6%AF%92%E9%A9%AC%E9%93%83%E8%96%AF%E6%B2%B9",
  "structured_content": {
    "默认分类": [
      "关于由马铃薯制成的外观相似的物品，请见“马铃薯油”。",
      "此条目描述的是一个愚人节玩笑版本24w14potato中的特性。",
      "此部分特性仅存在于该愚人节版本中，目前不计划添加到Minecraft的常规版本。",
      "请注意：该特性的本地化名称以愚人节翻译包为准，原版游戏内的相关内容显示为英文。"
    ],
    "[[|]]": [
      "[[|]]0.1"
    ],
    "最大堆叠": [
      "1"
    ],
    "poisonous_potato_oil": [
      "毒马铃薯油（Poisonous Potato Oil）是由毒马铃薯精炼后得到的物品，可以用来烧炼为毒树脂。"
    ],
    "精炼": [
      "在马铃薯精炼炉中精炼毒马铃薯可以精炼出毒马铃薯油，可以获得0.1 经验值，精炼时间需要125游戏刻（6.25秒）。"
    ],
    "马铃薯刷怪房": [
      "0.75",
      "1-4",
      "26.61%",
      "3.8"
    ],
    "马铃薯村庄房屋": [
      "0.13",
      "1",
      "12.07%",
      "8.3"
    ],
    "饮用": [
      "毒马铃薯油可以像药水一样，通过长按使用键饮用。",
      "饮用毒马铃薯油会获得1游戏刻（0.05秒）的非常滑效果和10秒（200游戏刻）的中毒效果。",
      "饮用后，会返还空玻璃瓶。"
    ],
    "烧炼": [
      "烧炼毒马铃薯油可获得杂质随机、清晰度为“糟糕”的毒树脂。烧炼时间为300游戏刻（15秒），比普通物品更慢。烧炼后，不会留下玻璃瓶。"
    ],
    "你知道吗": [
      "虽然毒马铃薯油拥有与药水相似的外观和功能，但毒马铃薯油的ID与药水不同，其也不存在“喷溅型毒马铃薯油”和“滞留型毒马铃薯油”物品。",
      "在创造模式物品栏中可以找到名为“毒马铃薯油”的物品以及其喷溅型和滞留型变种。但这些物品的ID为potion，即它们是具有毒马铃薯油药水效果的药水。因此这些物品也不能被用来烧炼获得毒树脂。",
      "这些药水形式的“毒马铃薯油”的瓶中液体呈现微微的淡绿色，而非真正的毒马铃薯油的白色。"
    ]
  }
}