{
  "title": "海晶石楼梯",
  "source_url": "https://zh.minecraft.wiki/w/%E6%B5%B7%E6%99%B6%E7%9F%B3%E6%A5%BC%E6%A2%AF",
  "structured_content": {
    "硬度": [
      "1.5",
      "1.5"
    ],
    "爆炸抗性": [
      "6"
    ],
    "地图基色": [
      "#4C7F99"
    ],
    "prismarine_stairs": [
      "海晶石楼梯（Prismarine Stairs）是海晶石制作的楼梯。"
    ],
    "最大堆叠": [
      "64"
    ],
    "生成": [
      "海晶石楼梯不会生成在世界中。"
    ],
    "[[|]][[|]][[|]][[|]][[|]][[|]]": [
      "[[|]]4"
    ],
    "破坏": [
      "挖掘海晶石楼梯的合适工具是镐。海晶石楼梯需要木镐或品质更好的镐来挖掘，否则挖掘时间将延长且不会掉落。"
    ],
    "徒手": [
      "7.5"
    ],
    "木质": [
      "1.15"
    ],
    "石质": [
      "0.6"
    ],
    "铜质": [
      "0.45"
    ],
    "铁质": [
      "0.4"
    ],
    "钻石质": [
      "0.3"
    ],
    "下界合金质": [
      "0.25"
    ],
    "金质": [
      "0.2"
    ],
    "效率": [
      "000"
    ],
    "急迫": [
      "001",
      "1JE0BE",
      "忽略其他影响因素而计算出的挖掘时间，单位：秒。更多信息详见挖掘 § 挖掘速度。",
      "海晶石楼梯被破坏后会掉落自身。"
    ],
    "用途": [
      "主条目：楼梯 § 用途"
    ],
    "音效": [
      "Java版："
    ],
    "本地化键名": [
      "方块：被破坏"
    ],
    "subtitles.block.generic.break": [
      "某物：摔落到方块上"
    ],
    "subtitles.block.generic.fall": [
      "方块：损坏中"
    ],
    "subtitles.block.generic.hit": [
      "方块：被放置"
    ],
    "subtitles.block.generic.footsteps": [
      "基岩版："
    ],
    "item.use.on": [
      "1.0",
      "0.8",
      "16"
    ],
    "break": [
      "1.0",
      "0.8-1",
      "16"
    ],
    "hit": [
      "0.37",
      "0.5",
      "16"
    ],
    "place": [
      "1.0",
      "0.8-1",
      "16"
    ],
    "fall": [
      "0.4",
      "1.0",
      "16"
    ],
    "step": [
      "0.3",
      "1.0",
      "16"
    ],
    "jump": [
      "0.12",
      "1.0",
      "16"
    ],
    "land": [
      "0.22",
      "1.0",
      "16"
    ],
    "ID": [
      "Java版："
    ],
    "block.minecraft.prismarine_stairs": [
      "基岩版："
    ],
    "方块状态": [
      "参见：方块状态",
      "Java版："
    ],
    "方块不含水": [
      "基岩版："
    ],
    "weirdo_direction": [
      "0"
    ],
    "楼梯面朝西方": [
      "1"
    ],
    "楼梯面朝东方": [
      "2"
    ],
    "楼梯面朝北方": [
      "3"
    ],
    "Java版": [
      "1.13",
      "18w07a",
      "加入了海晶石楼梯。",
      "1.14",
      "18w43a",
      "更改了海晶石楼梯的纹理。"
    ],
    "基岩版": [
      "1.2.13"
    ],
    "实验性玩法": [
      "1.2.13.8",
      "加入了海晶石楼梯。",
      "1.4.0",
      "1.2.14.2",
      "海晶石楼梯不再属于实验性玩法。",
      "1.10.0",
      "1.10.0.3",
      "更改了海晶石楼梯的纹理。"
    ],
    "原主机版": [
      "Xbox 360",
      "Xbox 360"
    ],
    "Xbox One": [
      "PS3",
      "PS4",
      "PS3",
      "PS4"
    ],
    "Switch": [
      "TU69",
      "1.76",
      "Patch 38",
      "加入了海晶石楼梯。",
      "1.90",
      "更改了海晶石楼梯的纹理。",
      "TU69",
      "1.76",
      "Patch 38",
      "加入了海晶石楼梯。",
      "1.90",
      "更改了海晶石楼梯的纹理。"
    ]
  }
}