{
  "title": "辅助程序与编辑器/NBTExplorer",
  "source_url": "https://zh.minecraft.wiki/w/%E8%BE%85%E5%8A%A9%E7%A8%8B%E5%BA%8F%E4%B8%8E%E7%BC%96%E8%BE%91%E5%99%A8%2FNBTExplorer",
  "structured_content": {
    "默认分类": [
      "该页面的内容不代表Mojang Studios或Minecraft Wiki的官方意见。"
    ],
    "NBTExplorer": [
      "NBTExplorer是一个低阶的Minecraft NBT图形界面编辑器。其界面为树形结构，可简便地浏览多个存档，并支持最新的NBT格式。NBTExplorer基于Substrate构建。由于任何Minecraft版本的地图大多基于NBT格式的文件，因此它通常可用于最新版的Minecraft而无需更新NBTExplorer。"
    ],
    "用法": [
      "NBT标签控制着一切世界参数，包括玩家的末影箱内容、物品栏、游戏模式、极限与否等。NBTExplorer可用于查看和编辑游戏数据，以下是一些典型案例：",
      "修改level.dat的相关内容，包括但不限于："
    ],
    "修改世界地形生成的设置，不会影响已生成的区块；": [
      "修改区块，包括但不限于："
    ],
    "修改实体数据或者删除实体，例如，若不慎产生超多实体而导致世界容易崩溃，用NBTExplorer可轻松去除过多实体；": [
      "修改方块实体的数据，包括命令方块、箱子、告示牌等。"
    ]
  }
}